vbi_evaluate_package/__init__.py
vbi_evaluate_package/evaluate.py
vbi_evaluate_package/extract.py
vbi_evaluate_package/fact_check.py
vbi_evaluate_package/image_check.py
vbi_evaluate_package/text_check.py
vbi_evaluate-0.3.3.dist-info/METADATA
vbi_evaluate-0.3.3.dist-info/WHEEL
vbi_evaluate-0.3.3.dist-info/top_level.txt
vbi_evaluate-0.3.3.dist-info/RECORD
