Metadata-Version: 2.4
Name: vbi-evaluate
Version: 0.3.3
Summary: A package for evaluating documents.
Home-page: https://github.com/yourusername/vbi-evaluate
Author: LeeMinHoon
Author-email: your_email@example.com
Classifier: Programming Language :: Python :: 3
Classifier: License :: OSI Approved :: MIT License
Classifier: Operating System :: OS Independent
Requires-Python: >=3.7
Requires-Dist: langchain-openai
Requires-Dist: langchain
Requires-Dist: python-dotenv
Requires-Dist: pymupdf
Requires-Dist: Pillow
Requires-Dist: trafilatura
Dynamic: author
Dynamic: author-email
Dynamic: classifier
Dynamic: description
Dynamic: description-content-type
Dynamic: home-page
Dynamic: requires-dist
Dynamic: requires-python
Dynamic: summary
